{
  "meta": {
    "counts": {
      "yes": 5,
      "no": 7,
      "partial": 4,
      "untested": 1
    },
    "total": 17,
    "last_updated": "2025-07-19T18:45:03.835Z"
  },
  "wallets": [
    {
      "wallet_name": "Phantom",
      "slug": "phantom",
      "categories": [
        "mobile",
        "extension"
      ],
      "platforms": [
        "ios",
        "android",
        "chrome",
        "firefox"
      ],
      "custody_model": "self",
      "solana_pay_qr": "yes",
      "solana_pay_notes": "QR works for SOL; limited token & invoice support. [DEX swap iOS]",
      "dex_swap": "yes",
      "nft_gallery": "yes",
      "staking": "no",
      "fiat_on": "yes",
      "fiat_off": "yes",
      "push_notifications": "yes",
      "multi_chain": true,
      "tested_version": "24.1.5",
      "tested_date": "2025-07-10",
      "tested_by": "Community Notion",
      "verified": true,
      "evidence_paths": [
        "public/evidence/phantom/ios/swap-quote.png",
        "public/evidence/phantom/ios/swap-success.png"
      ],
      "url": "https://phantom.app/"
    },
    {
      "wallet_name": "Solflare",
      "slug": "solflare",
      "categories": [
        "mobile",
        "extension"
      ],
      "platforms": [
        "ios",
        "android",
        "chrome",
        "firefox"
      ],
      "custody_model": "self",
      "solana_pay_qr": "yes",
      "solana_pay_notes": "Full Solana Pay QR support; seamless checkout.",
      "dex_swap": "yes",
      "nft_gallery": "yes",
      "staking": "yes",
      "fiat_on": "yes",
      "fiat_off": "yes",
      "push_notifications": "yes",
      "multi_chain": false,
      "tested_version": "3.2.0",
      "tested_date": "2025-07-10",
      "tested_by": "Community Notion",
      "verified": false,
      "evidence_paths": [],
      "url": "https://www.solflare.com/"
    },
    {
      "wallet_name": "Backpack",
      "slug": "backpack",
      "categories": [
        "mobile",
        "extension"
      ],
      "platforms": [
        "ios",
        "android",
        "chrome"
      ],
      "custody_model": "self",
      "solana_pay_qr": "no",
      "solana_pay_notes": "No Solana Pay QR; address send only.",
      "dex_swap": "yes",
      "nft_gallery": "no",
      "staking": "yes",
      "fiat_on": "yes",
      "fiat_off": "no",
      "push_notifications": "yes",
      "multi_chain": true,
      "tested_version": "1.5.2",
      "tested_date": "2025-07-10",
      "tested_by": "Community Notion",
      "verified": true,
      "evidence_paths": [
        "public/evidence/backpack/extension/stake-quote.png",
        "public/evidence/backpack/extension/stake-approve.png",
        "public/evidence/backpack/extension/stake-success.png"
      ],
      "url": "https://backpack.app/"
    },
    {
      "wallet_name": "Jupiter Wallet",
      "slug": "jupiter",
      "categories": [
        "mobile",
        "extension"
      ],
      "platforms": [
        "chrome",
        "firefox"
      ],
      "custody_model": "self",
      "solana_pay_qr": "no",
      "solana_pay_notes": "DEX-focused; no Solana Pay QR flow.",
      "dex_swap": "yes:jupiter",
      "nft_gallery": "no",
      "staking": "no",
      "fiat_on": "yes",
      "fiat_off": "no",
      "push_notifications": "no",
      "multi_chain": true,
      "tested_version": "1.1.3",
      "tested_date": "2025-07-12",
      "tested_by": "Community Notion",
      "verified": false,
      "evidence_paths": [],
      "url": "https://jup.ag/"
    },
    {
      "wallet_name": "Glow",
      "slug": "glow",
      "categories": [
        "mobile"
      ],
      "platforms": [
        "ios",
        "android"
      ],
      "custody_model": "self",
      "solana_pay_qr": "yes",
      "solana_pay_notes": "Smooth QR scan; intuitive UI; token send OK.",
      "dex_swap": "yes",
      "nft_gallery": "yes",
      "staking": "yes",
      "fiat_on": "no",
      "fiat_off": "no",
      "push_notifications": "yes",
      "multi_chain": false,
      "tested_version": "2.0.8",
      "tested_date": "2025-07-11",
      "tested_by": "Community Notion",
      "verified": false,
      "evidence_paths": [],
      "url": "https://glow.fun/"
    },
    {
      "wallet_name": "Bitget Wallet",
      "slug": "bitget",
      "categories": [
        "mobile"
      ],
      "platforms": [
        "ios",
        "android"
      ],
      "custody_model": "custodial",
      "solana_pay_qr": "yes",
      "solana_pay_notes": "QR works; checkout slightly slower (custodial).",
      "dex_swap": "yes",
      "nft_gallery": "yes",
      "staking": "yes",
      "fiat_on": "yes",
      "fiat_off": "yes",
      "push_notifications": "yes",
      "multi_chain": true,
      "tested_version": "6.7.0",
      "tested_date": "2025-07-12",
      "tested_by": "Community Notion",
      "verified": false,
      "evidence_paths": [],
      "url": "https://www.bitget.com/"
    },
    {
      "wallet_name": "OKX Wallet",
      "slug": "okx",
      "categories": [
        "mobile",
        "extension"
      ],
      "platforms": [
        "ios",
        "android",
        "chrome"
      ],
      "custody_model": "custodial",
      "solana_pay_qr": "partial",
      "solana_pay_notes": "Some Solana Pay flows work; token param flaky.",
      "dex_swap": "yes",
      "nft_gallery": "yes",
      "staking": "yes",
      "fiat_on": "yes",
      "fiat_off": "yes",
      "push_notifications": "yes",
      "multi_chain": true,
      "tested_version": "5.8.1",
      "tested_date": "2025-07-13",
      "tested_by": "Community Notion",
      "verified": false,
      "evidence_paths": [],
      "url": "https://www.okx.com/"
    },
    {
      "wallet_name": "Decaf",
      "slug": "decaf",
      "categories": [
        "mobile"
      ],
      "platforms": [
        "ios",
        "android"
      ],
      "custody_model": "custodial",
      "solana_pay_qr": "partial",
      "solana_pay_notes": "QR via linked web checkout; SOL ok.",
      "dex_swap": "no",
      "nft_gallery": "yes",
      "staking": "yes",
      "fiat_on": "no",
      "fiat_off": "no",
      "push_notifications": "no",
      "multi_chain": false,
      "tested_version": "0.9.4",
      "tested_date": "2025-07-11",
      "tested_by": "Community Notion",
      "verified": false,
      "evidence_paths": [],
      "url": "https://decaf.app/"
    },
    {
      "wallet_name": "Para",
      "slug": "para",
      "categories": [
        "extension"
      ],
      "platforms": [
        "chrome",
        "firefox"
      ],
      "custody_model": "self",
      "solana_pay_qr": "yes",
      "solana_pay_notes": "Full Solana Pay QR support in extension.",
      "dex_swap": "no",
      "nft_gallery": "no",
      "staking": "no",
      "fiat_on": "no",
      "fiat_off": "no",
      "push_notifications": "yes",
      "multi_chain": false,
      "tested_version": "1.0.3",
      "tested_date": "2025-07-15",
      "tested_by": "Community Notion",
      "verified": false,
      "evidence_paths": [],
      "url": "https://para.xyz/"
    },
    {
      "wallet_name": "Exodus",
      "slug": "exodus",
      "categories": [
        "mobile",
        "desktop"
      ],
      "platforms": [
        "ios",
        "android",
        "windows",
        "mac",
        "linux"
      ],
      "custody_model": "self",
      "solana_pay_qr": "no",
      "solana_pay_notes": "No Solana Pay; manual send; staking & fiat ramps.",
      "dex_swap": "yes",
      "nft_gallery": "yes",
      "staking": "yes",
      "fiat_on": "no",
      "fiat_off": "yes",
      "push_notifications": "no",
      "multi_chain": true,
      "tested_version": "24.3.0",
      "tested_date": "2025-07-14",
      "tested_by": "Community Notion",
      "verified": false,
      "evidence_paths": [],
      "url": "https://www.exodus.com/"
    },
    {
      "wallet_name": "TokenPocket",
      "slug": "tokenpocket",
      "categories": [
        "mobile",
        "extension"
      ],
      "platforms": [
        "ios",
        "android",
        "chrome",
        "firefox"
      ],
      "custody_model": "self",
      "solana_pay_qr": "partial",
      "solana_pay_notes": "Extension QR works; mobile needs extra steps.",
      "dex_swap": "yes",
      "nft_gallery": "yes",
      "staking": "no",
      "fiat_on": "yes",
      "fiat_off": "yes",
      "push_notifications": "yes",
      "multi_chain": true,
      "tested_version": "5.4.2",
      "tested_date": "2025-07-15",
      "tested_by": "Community Notion",
      "verified": false,
      "evidence_paths": [],
      "url": "https://www.tokenpocket.pro/"
    },
    {
      "wallet_name": "Coinbase Wallet",
      "slug": "coinbase",
      "categories": [
        "mobile",
        "extension"
      ],
      "platforms": [
        "ios",
        "android",
        "chrome",
        "firefox"
      ],
      "custody_model": "self",
      "solana_pay_qr": "partial",
      "solana_pay_notes": "QR works; cash-out slower; token support mixed.",
      "dex_swap": "yes",
      "nft_gallery": "yes",
      "staking": "no",
      "fiat_on": "yes",
      "fiat_off": "no",
      "push_notifications": "no",
      "multi_chain": true,
      "tested_version": "2025.06",
      "tested_date": "2025-07-15",
      "tested_by": "Community Notion",
      "verified": false,
      "evidence_paths": [],
      "url": "https://www.coinbase.com/"
    },
    {
      "wallet_name": "Trust Wallet",
      "slug": "trust",
      "categories": [
        "mobile"
      ],
      "platforms": [
        "ios",
        "android"
      ],
      "custody_model": "self",
      "solana_pay_qr": "untested",
      "solana_pay_notes": "Community data incomplete; Solana Pay not confirmed.",
      "dex_swap": "yes",
      "nft_gallery": "partial",
      "staking": "no",
      "fiat_on": "yes",
      "fiat_off": "no",
      "push_notifications": "yes",
      "multi_chain": true,
      "tested_by": "Community Notion",
      "verified": false,
      "evidence_paths": [],
      "url": "https://trustwallet.com/"
    },
    {
      "wallet_name": "Slope",
      "slug": "slope",
      "categories": [
        "mobile"
      ],
      "platforms": [
        "ios",
        "android"
      ],
      "custody_model": "self",
      "solana_pay_qr": "no",
      "solana_pay_notes": "No Solana Pay support.",
      "dex_swap": "no",
      "nft_gallery": "no",
      "staking": "no",
      "fiat_on": "no",
      "fiat_off": "no",
      "push_notifications": "no",
      "multi_chain": false,
      "tested_version": "1.3.7",
      "tested_date": "2025-07-13",
      "tested_by": "Community Notion",
      "verified": false,
      "evidence_paths": [],
      "url": "https://slope.finance/"
    },
    {
      "wallet_name": "Tangem",
      "slug": "tangem",
      "categories": [
        "hardware"
      ],
      "platforms": [
        "hardware"
      ],
      "custody_model": "hardware",
      "solana_pay_qr": "no",
      "solana_pay_notes": "NFC card; link payments only; no QR parse.",
      "dex_swap": "no",
      "nft_gallery": "yes",
      "staking": "no",
      "fiat_on": "no",
      "fiat_off": "no",
      "push_notifications": "no",
      "multi_chain": true,
      "tested_version": "Card FW 1.2",
      "tested_date": "2025-07-15",
      "tested_by": "Community Notion",
      "verified": false,
      "evidence_paths": [],
      "url": "https://tangem.com/"
    },
    {
      "wallet_name": "Ledger Live",
      "slug": "ledger",
      "categories": [
        "hardware",
        "desktop"
      ],
      "platforms": [
        "hardware",
        "ios",
        "android",
        "windows",
        "mac",
        "linux"
      ],
      "custody_model": "hardware",
      "solana_pay_qr": "no",
      "solana_pay_notes": "Needs Ledger Live companion; no QR scan.",
      "dex_swap": "no",
      "nft_gallery": "yes",
      "staking": "no",
      "fiat_on": "no",
      "fiat_off": "yes",
      "push_notifications": "no",
      "multi_chain": true,
      "tested_version": "Live App 2.7",
      "tested_date": "2025-07-15",
      "tested_by": "Community Notion",
      "verified": false,
      "evidence_paths": [],
      "url": "https://www.ledger.com/"
    },
    {
      "wallet_name": "SafePal",
      "slug": "safepal",
      "categories": [
        "hardware",
        "mobile"
      ],
      "platforms": [
        "hardware",
        "ios",
        "android"
      ],
      "custody_model": "hardware",
      "solana_pay_qr": "no",
      "solana_pay_notes": "Air-gapped; no Solana Pay QR.",
      "dex_swap": "no",
      "nft_gallery": "no",
      "staking": "no",
      "fiat_on": "no",
      "fiat_off": "no",
      "push_notifications": "no",
      "multi_chain": true,
      "tested_version": "1.0",
      "tested_date": "2025-07-15",
      "tested_by": "Community Notion",
      "verified": false,
      "evidence_paths": [],
      "url": "https://www.safepal.com/"
    }
  ]
}